fastapi_header_versioning/__init__.py
fastapi_header_versioning/fastapi.py
fastapi_header_versioning/openapi.py
fastapi_header_versioning/routing.py
fastapi_header_versioning-1.2.0.dist-info/LICENSE
fastapi_header_versioning-1.2.0.dist-info/WHEEL
fastapi_header_versioning-1.2.0.dist-info/METADATA
fastapi_header_versioning-1.2.0.dist-info/RECORD
