Metadata-Version: 2.1
Name: fastapi-header-versioning
Version: 1.2.0
Summary: API versioning based on header-provided data for FastAPI.
Home-page: https://github.com/tikon93/fastapi-header-versioning
License: MIT
Author: Timofey Petrenko
Author-email: timofey.petrenko93@gmail.com
Requires-Python: >=3.10,<4.0
Classifier: Development Status :: 5 - Production/Stable
Classifier: Environment :: Web Environment
Classifier: Framework :: AsyncIO
Classifier: Framework :: FastAPI
Classifier: Framework :: Pydantic
Classifier: Intended Audience :: Developers
Classifier: Intended Audience :: Information Technology
Classifier: Intended Audience :: System Administrators
Classifier: License :: OSI Approved :: MIT License
Classifier: Operating System :: OS Independent
Classifier: Programming Language :: Python
Classifier: Programming Language :: Python :: 3
Classifier: Programming Language :: Python :: 3.10
Classifier: Programming Language :: Python :: 3
Classifier: Topic :: Internet
Classifier: Topic :: Internet :: WWW/HTTP
Classifier: Topic :: Internet :: WWW/HTTP :: HTTP Servers
Classifier: Topic :: Software Development
Classifier: Topic :: Software Development :: Libraries
Classifier: Topic :: Software Development :: Libraries :: Application Frameworks
Classifier: Topic :: Software Development :: Libraries :: Python Modules
Classifier: Typing :: Typed
Requires-Dist: fastapi (>=0.96.1)
Requires-Dist: pydantic (>=1.10.0,<2.0.0)
Requires-Dist: typing-extensions
Project-URL: Repository, https://github.com/tikon93/fastapi-header-versioning
